flax_metrics/__init__.py
flax_metrics/base.py
flax_metrics/classification.py
flax_metrics/dot_product_ranking.py
flax_metrics/ranking.py
flax_metrics/regression.py
flax_metrics-0.4.0.dist-info/licenses/LICENSE
flax_metrics-0.4.0.dist-info/METADATA
flax_metrics-0.4.0.dist-info/WHEEL
flax_metrics-0.4.0.dist-info/top_level.txt
flax_metrics-0.4.0.dist-info/RECORD
