Metadata-Version: 2.4
Name: flax-metrics
Version: 0.4.0
Summary: Flax NXX implementation of common metrics.
Author: Till Hoffmann
License-Expression: BSD-3-Clause
Project-URL: Repository, https://github.com/tillahoffmann/flax-metrics
Project-URL: Documentation, https://flax-metrics.readthedocs.io/
Project-URL: Issues, https://github.com/tillahoffmann/flax-metrics/issues
Keywords: flax,jax,metrics,machine-learning
Classifier: Development Status :: 3 - Alpha
Classifier: Programming Language :: Python :: 3
Requires-Python: >=3.10
License-File: LICENSE
Requires-Dist: flax>=0.10.7
Dynamic: license-file
